__init__.py
football/__init__.py
football/xA.py
football/xG.py
football/xT.py
futsal/__init__.py
futsal/xA.py
futsal/xG.py
futsal/xT.py
goalytics-0.1.1.dist-info/licenses/LICENSE
goalytics-0.1.1.dist-info/METADATA
goalytics-0.1.1.dist-info/WHEEL
goalytics-0.1.1.dist-info/top_level.txt
goalytics-0.1.1.dist-info/RECORD
