Metadata-Version: 2.4
Name: goalytics
Version: 0.1.1
Summary: Goalytics is a modern Python library designed for advanced football analytics, focused on calculating and predicting key performance metrics like xG (Expected Goals), xA (Expected Assists), and xT (Expected Threat). 
Author-email: Kalinin Mitko <kalinin.mitko@gmail.com>
License: MIT License
Project-URL: Homepage, https://github.com/null-none/goalytics
Keywords: analytics,football,futsal,soccer,xg,xt,xa
Classifier: License :: OSI Approved :: MIT License
Classifier: Programming Language :: Python
Classifier: Programming Language :: Python :: 3
Requires-Python: >=3.9
License-File: LICENSE
Provides-Extra: dev
Requires-Dist: pip-tools; extra == "dev"
Dynamic: license-file
